{"type": "Feature", "id": 12515042, "properties": {"woe:id": 12515042, "woe:parent_id": 1049697, "woe:name": "Norfolk Island Airport", "woe:placetype": 14, "woe:placetype_name": "Airport", "woe:lang": "ENG", "iso:country": "NF", "meta:provider": ["geoplanet:7.3.1", "geoplanet:7.3.2", "geoplanet:7.4.0", "geoplanet:7.4.1", "geoplanet:7.5.1", "geoplanet:7.5.2", "geoplanet:7.6.0", "geoplanet:7.8.1", "geoplanet:7.9.0", "geoplanet:7.10.0", "geoplanet:8.0.0", "woeplanet:8.0.0"], "meta:indexed": "2020-08-20T20:49:06.715237", "woe:alias_ENG_V": ["NLK Airport", "NLK"], "meta:updated": "2020-08-22T02:46:49.299932", "woe:hierarchy": {"continent": 24865674, "country": 23424905, "town": 0, "planet": 1, "county": 0, "suburb": 0, "state": 0, "region": 0, "localadmin": 0}, "woe:timezone_id": 28350957, "woe:hash": "rdz6zdj529nt", "woe:centroid": [168.031799, -29.036301], "geom:latitude": -29.036301, "geom:longitude": 168.031799, "geom:hash": "rdz6zdj529nt", "woe:latitude": -29.036301, "geom:centroid": [168.031799, -29.036301], "woe:longitude": 168.031799, "woe:repo": "woeplanet-airport-nf"}, "geometry": {"coordinates": [168.031799, -29.036301], "type": "Point"}}